jekescore/__init__.py
jekescore/client.py
jekescore/models.py
jekescore-0.1.0.dist-info/METADATA
jekescore-0.1.0.dist-info/WHEEL
jekescore-0.1.0.dist-info/top_level.txt
jekescore-0.1.0.dist-info/RECORD
