Metadata-Version: 2.4
Name: jekescore
Version: 0.1.0
Summary: Scraper minimalista para datos de tiros de Sofascore
Author: El Jeke de las Deportivas
License: MIT
Project-URL: Homepage, https://github.com/jekedelasdeportivas/jekescore
Keywords: football,soccer,sofascore,scraper,shots,xg
Classifier: Development Status :: 3 - Alpha
Classifier: Intended Audience :: Developers
Classifier: License :: OSI Approved :: MIT License
Classifier: Programming Language :: Python :: 3.13
Requires-Python: >=3.13
Requires-Dist: requests>=2.28.0
Requires-Dist: pydantic>=2.0.0
Provides-Extra: dev
Requires-Dist: ruff>=0.14.0; extra == "dev"
Requires-Dist: pyright>=1.1.400; extra == "dev"
Requires-Dist: pytest>=8.0.0; extra == "dev"
Requires-Dist: pytest-cov>=4.0.0; extra == "dev"
